<?xml version="1.0" encoding="ISO-8859-1"?>
<root>
	<item id="Title"><![CDATA[Discuz! Plugin]]></item>
	<item id="Version"><![CDATA[X1]]></item>
    <item id="Data">
        <item id="plugin">
            <item id="name"><![CDATA[专区分享]]></item>
            <item id="version"><![CDATA[1.0]]></item>
            <item id="identifier"><![CDATA[groupshare]]></item>
			<item id="description"><![CDATA[专区分享]]></item>
            <item id="directory"><![CDATA[groupshare/]]></item>
			<item id="copyright"><![CDATA[China Telecom]]></item>
        </item>
        <item id="intro"><![CDATA[]]></item>
        <item id="installfile"><![CDATA[install.php]]></item>
        <item id="uninstallfile"><![CDATA[uninstall.php]]></item>
        <item id="version"><![CDATA[X1]]></item>
    </item>
</root>